control_plane_mcp/__init__.py
control_plane_mcp/__main__.py
control_plane_mcp/_version.py
control_plane_mcp/config.py
control_plane_mcp/server.py
control_plane_mcp/docs/resource_management_guide.md
control_plane_mcp/pydantic_generated/__init__.py
control_plane_mcp/pydantic_generated/abstractclustermodel.py
control_plane_mcp/pydantic_generated/deploymentrequestmodel.py
control_plane_mcp/pydantic_generated/facetsresourcemodel.py
control_plane_mcp/pydantic_generated/variablesmodel.py
control_plane_mcp/scripts/generate_pydantic_models.py
control_plane_mcp/tools/__init__.py
control_plane_mcp/tools/configure_resource_tool.py
control_plane_mcp/tools/env_override_tool.py
control_plane_mcp/tools/env_resource_tool.py
control_plane_mcp/tools/env_tools.py
control_plane_mcp/tools/project_tools.py
control_plane_mcp/tools/release_tools.py
control_plane_mcp/tools/resource_guide.py
control_plane_mcp/utils/__init__.py
control_plane_mcp/utils/client_utils.py
control_plane_mcp/utils/dict_utils.py
control_plane_mcp/utils/override_utils.py
control_plane_mcp/utils/validation_utils.py
facets_cp_mcp_server-0.1.1.dist-info/METADATA
facets_cp_mcp_server-0.1.1.dist-info/WHEEL
facets_cp_mcp_server-0.1.1.dist-info/entry_points.txt
facets_cp_mcp_server-0.1.1.dist-info/top_level.txt
facets_cp_mcp_server-0.1.1.dist-info/RECORD
