Metadata-Version: 2.4
Name: facets-cp-mcp-server
Version: 0.1.1
Summary: Facets Control Plane MCP Server
Author-email: Anshul Sao <anshul@facets.cloud>, Anuj Hydrabadi <anuj.hydrabadi@facets.cloud>
License: MIT
Project-URL: Homepage, https://github.com/Facets-cloud/control-plane-mcp-server
Project-URL: Bug Tracker, https://github.com/Facets-cloud/control-plane-mcp-server/issues
Project-URL: Documentation, https://github.com/Facets-cloud/control-plane-mcp-server#readme
Keywords: Facets,MCP,Control Plane,Python
Classifier: Programming Language :: Python :: 3
Classifier: Programming Language :: Python :: 3.12
Classifier: Programming Language :: Python :: 3.13
Classifier: License :: OSI Approved :: MIT License
Classifier: Operating System :: OS Independent
Classifier: Topic :: Software Development :: Libraries :: Python Modules
Classifier: Topic :: Software Development :: Build Tools
Classifier: Intended Audience :: Developers
Classifier: Development Status :: 4 - Beta
Requires-Python: >=3.12
Requires-Dist: mcp[cli]>=1.13.0
Requires-Dist: httpx>=0.25.0
Requires-Dist: facets-control-plane-sdk==1.0.3
Requires-Dist: pydantic~=2.11.2
Requires-Dist: jsonschema~=4.23.0
Requires-Dist: click<9.0.0,>=8.2.1
Requires-Dist: uvicorn<1.0.0,>=0.35.0
Requires-Dist: starlette<1.0.0,>=0.47.2
Requires-Dist: python-dotenv<2.0.0,>=1.1.1
